json2pytype/__init__.py
json2pytype/cli.py
json2pytype/code_generator.py
json2pytype/naming.py
json2pytype/structure_analyzer.py
json2pytype/type_inference.py
json2pytype-0.1.1.dist-info/METADATA
json2pytype-0.1.1.dist-info/WHEEL
json2pytype-0.1.1.dist-info/entry_points.txt
json2pytype-0.1.1.dist-info/top_level.txt
json2pytype-0.1.1.dist-info/RECORD
