Metadata-Version: 2.4
Name: json2pytype
Version: 0.1.1
Summary: A tool to generate Python classes with type hints from JSON files
Author-email: yjkindex <yangjingke@sjtu.edu.cn>
Classifier: Programming Language :: Python :: 3
Classifier: License :: OSI Approved :: MIT License
Classifier: Operating System :: OS Independent
Requires-Python: >=3.9
Provides-Extra: dev
Requires-Dist: pytest>=7.0; extra == "dev"
Requires-Dist: flake8>=4.0; extra == "dev"
Requires-Dist: black>=22.3.0; extra == "dev"
